importcheck/__init__.py
importcheck/__main__.py
importcheck/py.typed
importcheck-0.5.0.dist-info/LICENSE
importcheck-0.5.0.dist-info/METADATA
importcheck-0.5.0.dist-info/WHEEL
importcheck-0.5.0.dist-info/entry_points.txt
importcheck-0.5.0.dist-info/RECORD
