Metadata-Version: 2.1
Name: importcheck
Version: 0.5.0
Summary: A tool to check all modules can be correctly imported.
Author-email: Dominic Davis-Foster <dominic@davis-foster.co.uk>
License: MIT
Keywords: import,test
Home-page: https://github.com/python-coincidence/importcheck
Project-URL: Issue Tracker, https://github.com/python-coincidence/importcheck/issues
Project-URL: Source Code, https://github.com/python-coincidence/importcheck
Project-URL: Documentation, https://importcheck.readthedocs.io/en/latest
Platform: Windows
Platform: macOS
Platform: Linux
Classifier: Development Status :: 4 - Beta
Classifier: Environment :: Console
Classifier: Intended Audience :: Developers
Classifier: License :: OSI Approved :: MIT License
Classifier: Operating System :: OS Independent
Classifier: Programming Language :: Python
Classifier: Programming Language :: Python :: 3 :: Only
Classifier: Programming Language :: Python :: 3.6
Classifier: Programming Language :: Python :: 3.7
Classifier: Programming Language :: Python :: 3.8
Classifier: Programming Language :: Python :: 3.9
Classifier: Programming Language :: Python :: 3.10
Classifier: Programming Language :: Python :: 3.11
Classifier: Programming Language :: Python :: Implementation :: CPython
Classifier: Programming Language :: Python :: Implementation :: PyPy
Classifier: Typing :: Typed
Requires-Python: >=3.6
Requires-Dist: click>=7.1.2
Requires-Dist: consolekit>=1.0.0
Requires-Dist: dom-toml>=0.2.2
Requires-Dist: domdf-python-tools>=2.8.0
Requires-Dist: packaging>=20.9
Requires-Dist: typing-extensions>=3.7.4.3
